{
    "openstack_compute_quotaset_v2": {
        "status": "ASSESS",
        "layout": "openstack",
        "page_title": "OpenStack: openstack_compute_quotaset_v2",
        "sidebar_current": "docs-openstack-resource-compute-quotaset-v2",
        "description": "Manages a V2 compute quotaset resource within OpenStack.",
        "arguments": {
            "region": {
                "description": "The region in which to create the volume. If",
                "required": false,
                "policy": "",
                "notes": ""
            },
            "project_id": {
                "description": "ID of the project to manage quotas.",
                "required": true,
                "policy": "",
                "notes": ""
            },
            "fixed_ips": {
                "description": "Quota value for fixed IPs.",
                "required": false,
                "policy": "",
                "notes": ""
            },
            "floating_ips": {
                "description": "Quota value for floating IPs.",
                "required": false,
                "policy": "",
                "notes": ""
            },
            "injected_file_content_bytes": {
                "description": "Quota value for content bytes",
                "required": false,
                "policy": "",
                "notes": ""
            },
            "injected_file_path_bytes": {
                "description": "Quota value for path bytes of",
                "required": false,
                "policy": "",
                "notes": ""
            },
            "injected_files": {
                "description": "Quota value for injected files.",
                "required": false,
                "policy": "",
                "notes": ""
            },
            "key_pairs": {
                "description": "Quota value for key pairs.",
                "required": false,
                "policy": "",
                "notes": ""
            },
            "metadata_items": {
                "description": "Quota value for metadata items.",
                "required": false,
                "policy": "",
                "notes": ""
            },
            "ram": {
                "description": "Quota value for RAM.",
                "required": false,
                "policy": "",
                "notes": ""
            },
            "security_group_rules": {
                "description": "Quota value for security group rules.",
                "required": false,
                "policy": "",
                "notes": ""
            },
            "security_groups": {
                "description": "Quota value for security groups.",
                "required": false,
                "policy": "",
                "notes": ""
            },
            "cores": {
                "description": "Quota value for cores.",
                "required": false,
                "policy": "",
                "notes": ""
            },
            "instances": {
                "description": "Quota value for instances.",
                "required": false,
                "policy": "",
                "notes": ""
            },
            "server_groups": {
                "description": "Quota value for server groups.",
                "required": false,
                "policy": "",
                "notes": ""
            },
            "server_group_members": {
                "description": "Quota value for server groups members.",
                "required": false,
                "policy": "",
                "notes": ""
            }
        },
        "attributes": {
            "region": {
                "description": "See Argument Reference above."
            },
            "project_id": {
                "description": "See Argument Reference above."
            },
            "fixed_ips": {
                "description": "See Argument Reference above."
            },
            "floating_ips": {
                "description": "See Argument Reference above."
            },
            "injected_file_content_bytes": {
                "description": "See Argument Reference above."
            },
            "injected_file_path_bytes": {
                "description": "See Argument Reference above."
            },
            "injected_files": {
                "description": "See Argument Reference above."
            },
            "key_pairs": {
                "description": "See Argument Reference above."
            },
            "metadata_items": {
                "description": "See Argument Reference above."
            },
            "ram": {
                "description": "See Argument Reference above."
            },
            "security_group_rules": {
                "description": "See Argument Reference above."
            },
            "security_groups": {
                "description": "See Argument Reference above."
            },
            "cores": {
                "description": "See Argument Reference above."
            },
            "instances": {
                "description": "See Argument Reference above."
            },
            "server_groups": {
                "description": "See Argument Reference above."
            },
            "server_group_members": {
                "description": "See Argument Reference above."
            }
        },
        "timeouts": {}
    }
}