{
    "openstack_db_database_v1": {
        "status": "ASSESS",
        "layout": "openstack",
        "page_title": "OpenStack: openstack_db_database_v1",
        "sidebar_current": "docs-openstack-resource-db-database-v1",
        "description": "Manages a V1 database resource within OpenStack.",
        "arguments": {
            "name": {
                "description": "A unique name for the resource.",
                "required": false,
                "policy": "",
                "notes": ""
            },
            "instance_id": {
                "description": "The ID for the database instance.",
                "required": false,
                "policy": "",
                "notes": ""
            }
        },
        "attributes": {},
        "timeouts": {}
    }
}