{
    "tfe_team_members": {
        "status": "ASSESS",
        "layout": "tfe",
        "page_title": "Terraform Enterprise: tfe_team_members",
        "sidebar_current": "docs-resource-tfe-team-members",
        "description": "Manages users in a team.",
        "arguments": {
            "team_id": {
                "description": "ID of the team.",
                "required": false,
                "policy": "",
                "notes": ""
            },
            "usernames": {
                "description": "Names of the users to add.",
                "required": false,
                "policy": "",
                "notes": ""
            }
        },
        "attributes": {},
        "timeouts": {}
    }
}