{
    "vault_namespace": {
        "status": "ASSESS",
        "layout": "vault",
        "page_title": "Vault: vault_namespace resource",
        "sidebar_current": "docs-vault-resource-namespace",
        "description": "Writes namespaces for Vault",
        "arguments": {
            "path": {
                "description": "The path of the namespace. Must not have a trailing `/`",
                "required": false,
                "policy": "",
                "notes": ""
            }
        },
        "attributes": {},
        "timeouts": {}
    }
}