{
    "vault_transit_secret_backend_cache_config": {
        "status": "ASSESS",
        "layout": "vault",
        "page_title": "Vault: vault_transit_secret_backend_cache_config resource",
        "sidebar_current": "docs-vault-resource-transit-secret-backend-cache-config",
        "description": "Configure the cache for the Transit Secret Backend in Vault.",
        "arguments": {
            "backend": {
                "description": "The path the transit secret backend is mounted at, with no leading or trailing `/`s.",
                "required": false,
                "policy": "",
                "notes": ""
            },
            "size": {
                "description": "The number of cache entries. 0 means unlimited.",
                "required": false,
                "policy": "",
                "notes": ""
            }
        },
        "attributes": {},
        "timeouts": {}
    }
}